MANIFEST.in
setup.py
wbnlu/__init__.py
wbnlu/constants.py
wbnlu/dev_tools.py
wbnlu/logger.py
wbnlu/test.py
wbnlu/wbnlp.py
wbnlu.egg-info/PKG-INFO
wbnlu.egg-info/SOURCES.txt
wbnlu.egg-info/dependency_links.txt
wbnlu.egg-info/requires.txt
wbnlu.egg-info/top_level.txt
wbnlu/components/content_words.py
wbnlu/components/data_statistics.py
wbnlu/components/dictionary.py
wbnlu/components/edit.py
wbnlu/components/entity.py
wbnlu/components/knowledge_extractor.py
wbnlu/components/nlp_utils.py
wbnlu/components/parser.py
wbnlu/components/phrase.py
wbnlu/components/phrase_match.py
wbnlu/components/relation.py
wbnlu/components/rule_match.py
wbnlu/components/rule_segementer.py
wbnlu/components/seg_corrector.py
wbnlu/components/tagger.py
wbnlu/components/text_normalizer.py
wbnlu/components/wb_tag.py
wbnlu/components/wordpiece_tokenizer.py
wbnlu/configs/beauty_entity_config.yaml
wbnlu/configs/other_config.yml
wbnlu/configs/pattern_config.yml
wbnlu/configs/spacy_config.yml
wbnlu/logs/debug.log
wbnlu/logs/error.log
wbnlu/logs/info.log
wbnlu/logs/warning.log
wbnlu/midlevel/entity_recognition_module.py
wbnlu/midlevel/relation_recognition_module.py
wbnlu/midlevel/sentiment.py
wbnlu/resources/ambiguous_ne.txt
wbnlu/resources/features/emojis/emoji.txt
wbnlu/resources/features/entity/baike.per.seg.txt
wbnlu/resources/features/entity/beauty.atom.txt
wbnlu/resources/features/entity/beauty.effect.txt
wbnlu/resources/features/entity/beauty.ingredient.txt
wbnlu/resources/features/entity/beauty.txt
wbnlu/resources/features/entity/game.txt
wbnlu/resources/features/entity/games.txt
wbnlu/resources/features/entity/others.txt
wbnlu/resources/features/entity/sports.txt
wbnlu/resources/features/entity/time.txt
wbnlu/resources/features/segmentation/beauty.prod.txt
wbnlu/resources/features/segmentation/beauty.txt
wbnlu/resources/features/segmentation/sports.txt
wbnlu/resources/features/sentiment/features.txt
wbnlu/resources/features/timex/education.txt
wbnlu/resources/features/timex/entertainment.txt
wbnlu/resources/features/timex/fashion.txt
wbnlu/resources/features/timex/financial.txt
wbnlu/resources/features/timex/generic.txt
