Metadata-Version: 1.0
Name: wbnlu
Version: 2.3.4
Summary: WB NLU toolkit
Home-page: UNKNOWN
Author: UNKNOWN
Author-email: UNKNOWN
License: UNKNOWN
Platform: UNKNOWN
